[
  {
    "symbol": "SBIN",
    "spot": 1030.1,
    "currFut": 1048.64,
    "nextFut": 1049.67,
    "diffSpotFut": 1.8,
    "diffFutFut": 0.1,
    "timestamp": "2026-07-15 20:50:27.452134"
  },
  {
    "symbol": "RELIANCE",
    "spot": 1295.5,
    "currFut": 1318.82,
    "nextFut": 1320.11,
    "diffSpotFut": 1.8,
    "diffFutFut": 0.1,
    "timestamp": "2026-07-15 20:50:28.819294"
  },
  {
    "symbol": "INFY",
    "spot": 1076.3,
    "currFut": 1095.67,
    "nextFut": 1096.75,
    "diffSpotFut": 1.8,
    "diffFutFut": 0.1,
    "timestamp": "2026-07-15 20:50:30.189214"
  },
  {
    "symbol": "TCS",
    "spot": 2189.2,
    "currFut": 2228.61,
    "nextFut": 2230.79,
    "diffSpotFut": 1.8,
    "diffFutFut": 0.1,
    "timestamp": "2026-07-15 20:50:31.553083"
  },
  {
    "symbol": "HDFCBANK",
    "spot": 815.45,
    "currFut": 830.13,
    "nextFut": 830.94,
    "diffSpotFut": 1.8,
    "diffFutFut": 0.1,
    "timestamp": "2026-07-15 20:50:32.895910"
  }
]